acjnlp/__init__.py
acjnlp/utils.py
acjnlp-0.1.dist-info/LICENSE.txt
acjnlp-0.1.dist-info/METADATA
acjnlp-0.1.dist-info/WHEEL
acjnlp-0.1.dist-info/top_level.txt
acjnlp-0.1.dist-info/RECORD
