Metadata-Version: 2.1
Name: acjnlp
Version: 0.1
Summary: This is a natural language cleaning,preprocessing packages
Home-page: UNKNOWN
Author: akhil janardhan
Author-email: akhilchatgptcl@gmail.com
License: UNKNOWN
Platform: UNKNOWN
Classifier: Programming Language :: Python :: 3
Classifier: License :: OSI Approved :: MIT License
Classifier: Operating System :: OS Independent
License-File: LICENSE.txt
